chopin/__init__.py
chopin/chopin.py
chopin/compositions.py
chopin/contents.py
chopin/errors.py
chopin/data/compositions.json
chopin/data/contents.json
chopin-0.2.0.dist-info/LICENSE
chopin-0.2.0.dist-info/METADATA
chopin-0.2.0.dist-info/WHEEL
chopin-0.2.0.dist-info/top_level.txt
chopin-0.2.0.dist-info/RECORD
