Metadata-Version: 2.1
Name: chopin
Version: 0.2.0
Summary: chopin is a chopin package
Home-page: https://github.com/ster-phys/chopin
Author: ster
Author-email: ster.physics@gmail.com
License: MIT License
Classifier: Development Status :: 1 - Planning
Classifier: Programming Language :: Python :: 3.8
License-File: LICENSE
Requires-Dist: youtube-dl
